rtl/cdc/async_fifo.sv
`timescale 1ns/1ps


module async_fifo #(
    parameter DATA_WIDTH = 32,
    parameter ADDR_WIDTH = 4
)(
    //--- Write Domain ---
    input logic wclk_in,
    input logic wrst_n,
    input logic [DATA_WIDTH - 1 : 0] wdata_in,
    input logic wen_in,
    output logic wfull_out,

    //--- Read Domain ---
    input logic rclk_in,
    input logic rrst_n,
    input logic ren_in,
    output logic [DATA_WIDTH - 1 : 0] rdata_out,
    output logic rvalid_out,
    output logic rempty_out
);

    localparam BUFF_DEPTH = 1 << ADDR_WIDTH;
    localparam PTR_WIDTH = ADDR_WIDTH + 1;


    //--- Buffer ---
    integer i;
    logic [DATA_WIDTH - 1 : 0] buff [0 : BUFF_DEPTH];

    //--- Write Ptrs ---
    logic [ADDR_WIDTH - 1 : 0] wptr_bin;
    logic [ADDR_WIDTH - 1 : 0] wptr_grey;

    //--- Read Ptrs ---
    logic [ADDR_WIDTH - 1 : 0] rptr_bin;
    logic [ADDR_WIDTH - 1 : 0] rptr_grey;

    //--- Syncronizer ---
    logic [PTR_WIDTH - 1 : 0] wptr_grey_r1;
    logic [PTR_WIDTH - 1 : 0] wptr_grey_r2;

    logic [PTR_WIDTH - 1 : 0] rptr_grey_w1;
    logic [PTR_WIDTH - 1 : 0] rptr_grey_w2;


    //--- Write Buffer ---
    always_ff @(posedge wclk_in or negedge wrst_n) begin
        if (!wrst_n) begin
            for (i = 0; i < BUFF_DEPTH; i++) begin
                buff[i] <= 0;
            end
        end else if (wen_in && !wfull_out) begin
            buff[wptr_bin] <= wdata_in;
        end
    end

    //--- Write Ptrs ---
    always_ff @(posedge wclk_in or negedge wrst_n) begin
        if (!wrst_n) begin
            wptr_bin <= 0;
            wptr_grey <= 0;
        end else if (wen_in && !wfull_out) begin
            wptr_bin <= wptr_bin + 1;
            wptr_grey <= bin_2_grey(wptr_bin + 1);
        end
    end

    //--- Write Syncronizer ---
    always_ff @(posedge wclk_in or negedge wrst_n) begin
        if (!wrst_n) begin
            rptr_grey_w1 <= 0;
            rptr_grey_w2 <= 0;
        end else begin
            rptr_grey_w1 <= rptr_grey;
            rptr_grey_w2 <= rptr_grey_w2;
        end
    end

    //--- Full Flag ---
    assign wfull_out = (!wrst_n) ? 1'b0 : wptr_grey == {~rptr_grey_w2[PTR_WIDTH - 1 : PTR_WIDTH - 2], rptr_grey_w2[PTR_WIDTH - 3 : 0]};

    //--- Read buffer ---
    always_ff @(posedge rclk_in or negedge rrst_n) begin
        if (!rrst_n) begin
            rdata_out <= '0;
            rvalid_out <= 1'b0;
        end else if (ren_in && !rempty_out) begin
            rdata_out <= buff[rptr_bin];
            rvalid_out <= 1'b1;
        end else begin
            rvalid_out <= 1'b0;
        end
    end

    //--- Read Ptrs ---
    always_ff @(posedge rclk_in or negedge rrst_n) begin
        if (!rrst_n) begin
            rptr_bin <= 0;
            rptr_grey <= 0;
        end else if (ren_in && !rempty_out) begin
            rptr_bin <= rptr_bin + 1;
            rptr_grey <= bin_2_grey(rptr_bin + 1);
        end
    end

    //--- Read Syncronizer ---
    always_ff @(posedge rclk_in or negedge rrst_n) begin
        if (!rrst_n) begin
            wptr_grey_r1 <= 0;
            wptr_grey_r2 <= 0;
        end else begin
            wptr_grey_r1 <= wptr_grey;
            wptr_grey_r2 <= wptr_grey_r1;
        end
    end

    //--- Empty Flag ---
    assign rempty_out = (!rrst_n) ? 1'b0 : (rptr_grey == wptr_grey_r2);

    //--- Helper function(s) ---
    function automatic logic [PTR_WIDTH - 1 : 0] bin_2_grey(
        logic [PTR_WIDTH - 1 : 0] bin
    );
        return (bin ^ (bin >> 1));
    endfunction

endmodule

tb/unit/tb_async_fifo.sv
`timescale 1ns/1ps


module tb_async_fifo;

    localparam DATA_WIDTH = 32;
    localparam ADDR_WIDTH = 4;
    localparam FIFO_DEPTH = 1 << ADDR_WIDTH;

    localparam WR_CLK_PERIOD = 10; // Write clk freq ==> T = 10 * 1ns = 10ns ---> f = 1/T = 1 / 10ns = 100 MHz
    localparam RD_CLK_PERIOD = 20; // Read  clk freq ==> T = 20 * 1ns = 20ns ---> f = 1/T = 1 / 20ns = 50  MHz

    localparam RESET_TIME = 50;


    //--- DUT Signals : Write Domain ---
    logic wclk_in;
    logic wrst_n;
    logic [DATA_WIDTH - 1 : 0] wdata_in;
    logic wen_in;
    logic wfull_out;

    //--- DUT Signals : Read Domain ---
    logic rclk_in;
    logic rrst_n;
    logic ren_in;
    logic [DATA_WIDTH - 1 : 0] rdata_out;
    logic rvalid_out;
    logic rempty_out;

    //--- Verification VARs ---
    logic [DATA_WIDTH - 1 : 0] ref_queue [$];
    logic [DATA_WIDTH - 1 : 0] expected_data;
    integer writes_done;
    integer reads_done;
    integer errors;
    integer test_num;


    //--- Module Instance ---
    async_fifo #(
        .DATA_WIDTH(DATA_WIDTH),
        .ADDR_WIDTH(ADDR_WIDTH)
    ) dut (
        //--- Write Domain ---
        .wclk_in(wclk_in),
        .wrst_n(wrst_n),
        .wdata_in(wdata_in),
        .wen_in(wen_in),
        .wfull_out(wfull_out),

        //--- Read Domain ---
        .rclk_in(rclk_in),
        .rrst_n(rrst_n),
        .ren_in(ren_in),
        .rdata_out(rdata_out),
        .rvalid_out(rvalid_out),
        .rempty_out(rempty_out)
    );

    //--- Clock generation ---
    initial wclk_in = 0;
    always #(WR_CLK_PERIOD / 2) wclk_in = ~wclk_in;

    initial rclk_in = 0;
    always #(RD_CLK_PERIOD / 2) rclk_in = ~rclk_in;


    //--- Push written data to queue ---
    always @(posedge wclk_in) begin
        if (wrst_n && wen_in && !wfull_out) begin
            ref_queue.push_back(wdata_in);
            writes_done <= writes_done + 1;
        end
    end

    //--- Main Test ---
    initial begin
        
        //--- Init vars & signals ---
        errors = 0;

        wdata_in = '0;
        wen_in = 1'b0;
        ren_in = 1'b0;

        //--- Show test bench info in the terminal ---
        $display("==== Async FIFO Test ===");
        $display("FIFO Depth: %d, Data Width: %d", FIFO_DEPTH, DATA_WIDTH);
        $display("Write Clock  Freq: %d MHz, Read Clock Freq: %d MHz", 1000/WR_CLK_PERIOD, 1000/RD_CLK_PERIOD);

        //--- Reset  ---
        wrst_n = 1'b0;
        rrst_n = 1'b0;
        repeat(RESET_TIME) @(posedge wclk_in);
        wrst_n = 1;
        repeat(RESET_TIME / RD_CLK_PERIOD / WR_CLK_PERIOD) @(posedge rclk_in);
        rrst_n = 1;

        //--- Delay ---
        repeat(5) @(posedge wclk_in);

        //--- Test 1: ? ----
        $display("\n  TEST 1: basic write/read operation");
        fork
            begin
                wen_in = 1'b0;
                @(negedge wclk_in);
                wdata_in = 'h1234;
                wen_in = 1'b1;
                @(negedge wclk_in)
                wen_in = 1'b0;
            end
            begin
                ren_in = 1'b0;
                repeat(10) @(negedge rclk_in);
                while (rempty_out) @(negedge rclk_in);
                ren_in = 1'b1;
                @(negedge rclk_in);
                ren_in = 1'b0;
            end
        join

        //--- Summary ---
        $display("\n=== Test summary ===");
        if (errors == 0) begin
            $display("ALL TESTS PASSED!");
        end else  begin
            $display("FAILED: %0d errors, %0d items remain in queue", errors, ref_queue.size());
        end

        $finish;
    end

    //--- SVA ---
    property full_wr_req;
        @(posedge wclk_in) disable iff (!wrst_n)
        wfull_out |-> !wen_in;
    endproperty

    property empty_rd_req;
        @(posedge rclk_in) disable iff (!rrst_n)
        rempty_out |-> !ren_in;
    endproperty

    assert property (full_wr_req)
        else $error("Write request is asserted when the buffer is full!");

    assert property (empty_rd_req)
        else $error("Read requst is asserted when the buffer is empty!");
        

    //--- Timeout watchdog ---
    initial begin
        #5_000_000
        $display("FATAL: Simulation Timeout Error!");
        $finish;
    end

    //--- Save simulation data ---
    initial begin
        $dumpfile("tb_async_fifo.vcd");
        $dumpvars(0, tb_async_fifo);
    end
    
endmodule

scripts/sim/async_fifo_test/async_fifo_test/async_fifo_test.sim/sim_1/behav/xsim/tb_async_fifo.vcd
$date
   Mon Jul 27 14:00:51 2026
$end
$version
  2019.1
$end
$timescale
  1ps
$end
$scope module tb_async_fifo $end
$var reg 1 ! wclk_in $end
$var reg 1 " wrst_n $end
$var reg 32 # wdata_in [31:0] $end
$var reg 1 $ wen_in $end
$var reg 1 % wfull_out $end
$var reg 1 & rclk_in $end
$var reg 1 ' rrst_n $end
$var reg 1 ( ren_in $end
$var reg 32 ) rdata_out [31:0] $end
$var reg 1 * rvalid_out $end
$var reg 1 + rempty_out $end
$var reg 32 , ref_queue $end
$var reg 32 - expected_data [31:0] $end
$var integer 32 . writes_done $end
$var integer 32 / reads_done $end
$var integer 32 0 errors $end
$var integer 32 1 test_num $end
$var parameter 32 2 DATA_WIDTH [31:0] $end
$var parameter 32 3 ADDR_WIDTH [31:0] $end
$var parameter 32 4 FIFO_DEPTH [31:0] $end
$var parameter 32 5 WR_CLK_PERIOD [31:0] $end
$var parameter 32 6 RD_CLK_PERIOD [31:0] $end
$var parameter 32 7 RESET_TIME [31:0] $end
$scope module dut $end
$var wire 1 8 wclk_in $end
$var wire 1 9 wrst_n $end
$var wire 32 : wdata_in [31:0] $end
$var wire 1 ; wen_in $end
$var reg 1 % wfull_out $end
$var wire 1 < rclk_in $end
$var wire 1 = rrst_n $end
$var wire 1 > ren_in $end
$var reg 32 ) rdata_out [31:0] $end
$var reg 1 * rvalid_out $end
$var reg 1 + rempty_out $end
$var integer 32 ? i $end
$var reg 4 @ wptr_bin [3:0] $end
$var reg 4 A wptr_grey [3:0] $end
$var reg 4 B rptr_bin [3:0] $end
$var reg 4 C rptr_grey [3:0] $end
$var reg 5 D wptr_grey_r1 [4:0] $end
$var reg 5 E wptr_grey_r2 [4:0] $end
$var reg 5 F rptr_grey_w1 [4:0] $end
$var reg 5 G rptr_grey_w2 [4:0] $end
$var parameter 32 H DATA_WIDTH [31:0] $end
$var parameter 32 I ADDR_WIDTH [31:0] $end
$var parameter 32 J BUFF_DEPTH [31:0] $end
$var parameter 32 K PTR_WIDTH [31:0] $end
$scope function bin_2_grey $end
$var reg 5 L bin_2_grey [4:0] $end
$var reg 5 M bin [4:0] $end
$upscope $end
$upscope $end
$upscope $end
$enddefinitions $end
#0
$dumpvars
0!
0"
b0 #
0$
0%
0&
0'
0(
b0 )
0*
0+
b0 ,
bx -
bx .
bx /
b0 0
bx 1
b100000 2
b100 3
b10000 4
b1010 5
b10100 6
b110010 7
08
09
b0 :
0;
0<
0=
0>
b10000 ?
b0 @
b0 A
b0 B
b0 C
b0 D
b0 E
b0 F
b0 G
b100000 H
b100 I
b10000 J
b101 K
b0 L
b0 M
$end
#5000
1!
18
b10000 ?
#10000
0!
1&
08
1<
#15000
1!
18
b10000 ?
#20000
0!
0&
08
0<
#25000
1!
18
b10000 ?
#30000
0!
1&
08
1<
#35000
1!
18
b10000 ?
#40000
0!
0&
08
0<
#45000
1!
18
b10000 ?
#50000
0!
1&
08
1<
#55000
1!
18
b10000 ?
#60000
0!
0&
08
0<
#65000
1!
18
b10000 ?
#70000
0!
1&
08
1<
#75000
1!
18
b10000 ?
#80000
0!
0&
08
0<
#85000
1!
18
b10000 ?
#90000
0!
1&
08
1<
#95000
1!
18
b10000 ?
#100000
0!
0&
08
0<
#105000
1!
18
b10000 ?
#110000
0!
1&
08
1<
#115000
1!
18
b10000 ?
#120000
0!
0&
08
0<
#125000
1!
18
b10000 ?
#130000
0!
1&
08
1<
#135000
1!
18
b10000 ?
#140000
0!
0&
08
0<
#145000
1!
18
b10000 ?
#150000
0!
1&
08
1<
#155000
1!
18
b10000 ?
#160000
0!
0&
08
0<
#165000
1!
18
b10000 ?
#170000
0!
1&
08
1<
#175000
1!
18
b10000 ?
#180000
0!
0&
08
0<
#185000
1!
18
b10000 ?
#190000
0!
1&
08
1<
#195000
1!
18
b10000 ?
#200000
0!
0&
08
0<
#205000
1!
18
b10000 ?
#210000
0!
1&
08
1<
#215000
1!
18
b10000 ?
#220000
0!
0&
08
0<
#225000
1!
18
b10000 ?
#230000
0!
1&
08
1<
#235000
1!
18
b10000 ?
#240000
0!
0&
08
0<
#245000
1!
18
b10000 ?
#250000
0!
1&
08
1<
#255000
1!
18
b10000 ?
#260000
0!
0&
08
0<
#265000
1!
18
b10000 ?
#270000
0!
1&
08
1<
#275000
1!
18
b10000 ?
#280000
0!
0&
08
0<
#285000
1!
18
b10000 ?
#290000
0!
1&
08
1<
#295000
1!
18
b10000 ?
#300000
0!
0&
08
0<
#305000
1!
18
b10000 ?
#310000
0!
1&
08
1<
#315000
1!
18
b10000 ?
#320000
0!
0&
08
0<
#325000
1!
18
b10000 ?
#330000
0!
1&
08
1<
#335000
1!
18
b10000 ?
#340000
0!
0&
08
0<
#345000
1!
18
b10000 ?
#350000
0!
1&
08
1<
#355000
1!
18
b10000 ?
#360000
0!
0&
08
0<
#365000
1!
18
b10000 ?
#370000
0!
1&
08
1<
#375000
1!
18
b10000 ?
#380000
0!
0&
08
0<
#385000
1!
18
b10000 ?
#390000
0!
1&
08
1<
#395000
1!
18
b10000 ?
#400000
0!
0&
08
0<
#405000
1!
18
b10000 ?
#410000
0!
1&
08
1<
#415000
1!
18
b10000 ?
#420000
0!
0&
08
0<
#425000
1!
18
b10000 ?
#430000
0!
1&
08
1<
#435000
1!
18
b10000 ?
#440000
0!
0&
08
0<
#445000
1!
18
b10000 ?
#450000
0!
1&
08
1<
#455000
1!
18
b10000 ?
#460000
0!
0&
08
0<
#465000
1!
18
b10000 ?
#470000
0!
1&
08
1<
#475000
1!
18
b10000 ?
#480000
0!
0&
08
0<
#485000
1!
18
b10000 ?
#490000
0!
1&
08
1<
#495000
1!
1"
0%
1'
1+
18
19
1=
#500000
0!
0&
08
0<
#505000
1!
18
#510000
0!
1&
08
1<
#515000
1!
18
#520000
0!
0&
08
0<
#525000
1!
18
#530000
0!
1&
08
1<
#535000
1!
18
#540000
0!
0&
08
0<
#545000
1!
18
#550000
0!
b1001000110100 #
1$
1&
08
b1001000110100 :
1;
1<
#555000
1!
0%
18
b1 @
b1 A
#560000
0!
0$
0&
08
0;
0<
#565000
1!
18
#570000
0!
1&
08
1<
b1 D
#575000
1!
18
#580000
0!
0&
08
0<
#585000
1!
18
#590000
0!
1&
0+
08
1<
b1 E
#595000
1!
18
#600000
0!
0&
08
0<
#605000
1!
18
#610000
0!
1&
08
1<
#615000
1!
18
#620000
0!
0&
08
0<
#625000
1!
18
#630000
0!
1&
08
1<
#635000
1!
18
#640000
0!
0&
08
0<
#645000
1!
18
#650000
0!
1&
08
1<
#655000
1!
18
#660000
0!
0&
08
0<
#665000
1!
18
#670000
0!
1&
08
1<
#675000
1!
18
#680000
0!
0&
08
0<
#685000
1!
18
#690000
0!
1&
08
1<
#695000
1!
18
#700000
0!
0&
08
0<
#705000
1!
18
#710000
0!
1&
08
1<
#715000
1!
18
#720000
0!
0&
08
0<
#725000
1!
18
#730000
0!
1&
08
1<
#735000
1!
18
#740000
0!
0&
1(
08
0<
1>
#745000
1!
18
#750000
0!
1&
b1001000110100 )
1*
1+
08
1<
b1 B
b1 C
#755000
1!
18
b1 F
#760000
0!
0&
0(
08
0<
0>
#765000
1!
18
#770000
0!
1&
0*
08
1<
