rtl/timestamp/timestamp_counter.sv
`timescale 1ns/1ps


module timestamp_counter #(
    parameter INPUT_CLK_FREQ_HZ = 50_000_000
) (
    input logic clk,
    input logic rst_n,

    output logic [31 : 0] timestamp,

    output logic tick_1us
);

    localparam CLKS_PER_1US = INPUT_CLK_FREQ_HZ / 1_000_000 - 1;
    localparam CNT_WIDTH = $clog2(CLKS_PER_1US + 1);

    
    logic [CNT_WIDTH - 1 : 0] timer_cnt;


    //--- timer_cnt ---
    always_ff @(posedge clk or negedge rst_n ) begin
        if (!rst_n) begin
            timer_cnt <= '0;
        end else begin
            if (timer_cnt == CLKS_PER_1US) begin
                timer_cnt <= '0;
            end else begin
                timer_cnt <= timer_cnt + 1;
            end
        end
    end


    //--- tick_1us ---
    always_ff @(posedge clk or negedge rst_n) begin
        if (!rst_n) begin
            tick_1us <= 1'b0;
        end else if (timer_cnt == CLKS_PER_1US) begin
            tick_1us <= 1'b1;
        end else begin
            tick_1us <= 1'b0;
        end
    end


    //--- Free running timestamp ---
    always_ff @(posedge clk or negedge rst_n) begin
        if (!rst_n) begin
            timestamp <= '0;
        end else if (tick_1us) begin
            timestamp <= timestamp + 1'b1;
        end
    end


endmodule

tb/unit/tb_timestamp_counter.sv
`timescale 1ns/1ps


module tb_timestamp_counter;

    localparam INPUT_CLK_FREQ_HZ = 50_000_000;

    logic clk;
    logic rst_n;
    logic [31 : 0] timestamp;
    logic tick_1us;

    timestamp_counter #(
        .INPUT_CLK_FREQ_HZ(INPUT_CLK_FREQ_HZ)
    ) dut (
        .clk(clk),
        .rst_n(rst_n),
        .timestamp(timestamp),
        .tick_1us(tick_1us)
    );

    initial clk = 0;
    always #(10) clk = ~clk; // freq = 1 / 20ns = 1_000_000_000 / 20 = 50_000_000 MHz

    initial begin

        //--- Reset ---
        rst_n = 1'b0;
        repeat(10) @(posedge clk);
        rst_n = 1'b1;

        //--- Test 1 ---

        repeat(10 * 50) @(posedge clk);
        $finish;

    end

    //--- SVA ---
    property one_cycle_tick_1us;
        @(posedge clk) disable iff (!rst_n)
        tick_1us |=> !tick_1us;
    endproperty

    assert property (one_cycle_tick_1us) 
        else   $error("The tick_1us is more than one cycle!");

    //--- Simulation timeout watchdog ---
    initial begin
        #5_000_000
        $display("Warning: Simulation Timeour!");
        $finish;
    end

    //--- Save results ---
    initial begin
        $dumpfile("tb_timestamp_counter.vcd");
        $dumpvars(0, tb_timestamp_counter);
    end

endmodule

scripts/sim/timestamp_counter_test/timestamp_counter_test/timestamp_counter_test.sim/sim_1/behav/xsim/tb_timestamp_counter.vcd
$date
   Tue Jul 28 11:06:43 2026
$end
$version
  2019.1
$end
$timescale
  1ps
$end
$scope module tb_timestamp_counter $end
$var reg 1 ! clk $end
$var reg 1 " rst_n $end
$var reg 32 # timestamp [31:0] $end
$var reg 1 $ tick_1us $end
$var parameter 32 % INPUT_CLK_FREQ_HZ [31:0] $end
$scope module dut $end
$var wire 1 & clk $end
$var wire 1 ' rst_n $end
$var reg 32 # timestamp [31:0] $end
$var reg 1 $ tick_1us $end
$var reg 6 ( timer_cnt [5:0] $end
$var parameter 32 ) INPUT_CLK_FREQ_HZ [31:0] $end
$var parameter 32 * CLKS_PER_1US [31:0] $end
$var parameter 32 + CNT_WIDTH [31:0] $end
$upscope $end
$upscope $end
$enddefinitions $end
#0
$dumpvars
0!
0"
b0 #
0$
b10111110101111000010000000 %
0&
0'
b0 (
b10111110101111000010000000 )
b110001 *
b110 +
$end
#10000
1!
1&
#20000
0!
0&
#30000
1!
1&
#40000
0!
0&
#50000
1!
1&
#60000
0!
0&
#70000
1!
1&
#80000
0!
0&
#90000
1!
1&
#100000
0!
0&
#110000
1!
1&
#120000
0!
0&
#130000
1!
1&
#140000
0!
0&
#150000
1!
1&
#160000
0!
0&
#170000
1!
1&
#180000
0!
0&
#190000
1!
1"
1&
1'
b1 (
#200000
0!
0&
#210000
1!
1&
b10 (
#220000
0!
0&
#230000
1!
1&
b11 (
#240000
0!
0&
#250000
1!
1&
b100 (
#260000
0!
0&
#270000
1!
1&
b101 (
#280000
0!
0&
#290000
1!
1&
b110 (
#300000
0!
0&
#310000
1!
1&
b111 (
#320000
0!
0&
#330000
1!
1&
b1000 (
#340000
0!
0&
#350000
1!
1&
b1001 (
#360000
0!
0&
#370000
1!
1&
b1010 (
#380000
0!
0&
#390000
1!
1&
b1011 (
#400000
0!
0&
#410000
1!
1&
b1100 (
#420000
0!
0&
#430000
1!
1&
b1101 (
#440000
0!
0&
#450000
1!
1&
b1110 (
#460000
0!
0&
#470000
1!
1&
b1111 (
#480000
0!
0&
#490000
1!
1&
b10000 (
#500000
0!
0&
#510000
1!
1&
b10001 (
#520000
0!
0&
#530000
1!
1&
b10010 (
#540000
0!
0&
#550000
1!
1&
b10011 (
#560000
0!
0&
#570000
1!
1&
b10100 (
#580000
0!
0&
#590000
1!
1&
b10101 (
#600000
0!
0&
#610000
1!
1&
b10110 (
#620000
0!
0&
#630000
1!
1&
b10111 (
#640000
0!
0&
#650000
1!
1&
b11000 (
#660000
0!
0&
#670000
1!
1&
b11001 (
#680000
0!
0&
#690000
1!
1&
b11010 (
#700000
0!
0&
#710000
1!
1&
b11011 (
#720000
0!
0&
#730000
1!
1&
b11100 (
#740000
0!
0&
#750000
1!
1&
b11101 (
#760000
0!
0&
#770000
1!
1&
b11110 (
#780000
0!
0&
#790000
1!
1&
b11111 (
#800000
0!
0&
#810000
1!
1&
b100000 (
#820000
0!
0&
#830000
1!
1&
b100001 (
#840000
0!
0&
#850000
1!
1&
b100010 (
#860000
0!
0&
#870000
1!
1&
b100011 (
#880000
0!
0&
#890000
1!
1&
b100100 (
#900000
0!
0&
#910000
1!
1&
b100101 (
#920000
0!
0&
#930000
1!
1&
b100110 (
#940000
0!
0&
#950000
1!
1&
b100111 (
#960000
0!
0&
#970000
1!
1&
b101000 (
#980000
0!
0&
#990000
1!
1&
b101001 (
#1000000
0!
0&
#1010000
1!
1&
b101010 (
#1020000
0!
0&
#1030000
1!
1&
b101011 (
#1040000
0!
0&
#1050000
1!
1&
b101100 (
#1060000
0!
0&
#1070000
1!
1&
b101101 (
#1080000
0!
0&
#1090000
1!
1&
b101110 (
#1100000
0!
0&
#1110000
1!
1&
b101111 (
#1120000
0!
0&
#1130000
1!
1&
b110000 (
#1140000
0!
0&
#1150000
1!
1&
b110001 (
#1160000
0!
0&
#1170000
1!
1$
1&
b0 (
#1180000
0!
0&
#1190000
1!
b1 #
0$
1&
b1 (
#1200000
0!
0&
#1210000
1!
1&
b10 (
#1220000
0!
0&
#1230000
1!
1&
b11 (
#1240000
0!
0&
#1250000
1!
1&
b100 (
#1260000
0!
0&
#1270000
1!
1&
b101 (
#1280000
0!
0&
#1290000
1!
1&
b110 (
#1300000
0!
0&
#1310000
1!
1&
b111 (
#1320000
0!
0&
#1330000
1!
1&
b1000 (
#1340000
0!
0&
#1350000
1!
1&
b1001 (
#1360000
0!
0&
#1370000
1!
1&
b1010 (
#1380000
0!
0&
#1390000
1!
1&
b1011 (
#1400000
0!
0&
#1410000
1!
1&
b1100 (
#1420000
0!
0&
#1430000
1!
1&
b1101 (
#1440000
0!
0&
#1450000
1!
1&
b1110 (
#1460000
0!
0&
#1470000
1!
1&
b1111 (
#1480000
0!
0&
#1490000
1!
1&
b10000 (
#1500000
0!
0&
#1510000
1!
1&
b10001 (
#1520000
0!
0&
#1530000
1!
1&
b10010 (
#1540000
0!
0&
#1550000
1!
1&
b10011 (
#1560000
0!
0&
#1570000
1!
1&
b10100 (
#1580000
0!
0&
#1590000
1!
1&
b10101 (
#1600000
0!
0&
#1610000
1!
1&
b10110 (
#1620000
0!
0&
#1630000
1!
1&
b10111 (
#1640000
0!
0&
#1650000
1!
1&
b11000 (
#1660000
0!
0&
#1670000
1!
1&
b11001 (
#1680000
0!
0&
#1690000
1!
1&
b11010 (
#1700000
0!
0&
#1710000
1!
1&
b11011 (
#1720000
0!
0&
#1730000
1!
1&
b11100 (
#1740000
0!
0&
#1750000
1!
1&
b11101 (
#1760000
0!
0&
#1770000
1!
1&
b11110 (
#1780000
0!
0&
#1790000
1!
1&
b11111 (
#1800000
0!
0&
#1810000
1!
1&
b100000 (
#1820000
0!
0&
#1830000
1!
1&
b100001 (
#1840000
0!
0&
#1850000
1!
1&
b100010 (
#1860000
0!
0&
#1870000
1!
1&
b100011 (
#1880000
0!
0&
#1890000
1!
1&
b100100 (
#1900000
0!
0&
#1910000
1!
1&
b100101 (
#1920000
0!
0&
#1930000
1!
1&
b100110 (
#1940000
0!
0&
#1950000
1!
1&
b100111 (
#1960000
0!
0&
#1970000
1!
1&
b101000 (
#1980000
0!
0&
#1990000
1!
1&
b101001 (
#2000000
0!
0&
#2010000
1!
1&
b101010 (
#2020000
0!
0&
#2030000
1!
1&
b101011 (
#2040000
0!
0&
#2050000
1!
1&
b101100 (
#2060000
0!
0&
#2070000
1!
1&
b101101 (
#2080000
0!
0&
#2090000
1!
1&
b101110 (
#2100000
0!
0&
#2110000
1!
1&
b101111 (
#2120000
0!
0&
#2130000
1!
1&
b110000 (
#2140000
0!
0&
#2150000
1!
1&
b110001 (
#2160000
0!
0&
#2170000
1!
1$
1&
b0 (
#2180000
0!
0&
#2190000
1!
b10 #
0$
1&
b1 (
#2200000
0!
0&
#2210000
1!
1&
b10 (
#2220000
0!
0&
#2230000
1!
1&
b11 (
#2240000
0!
0&
#2250000
1!
1&
b100 (
#2260000
0!
0&
#2270000
1!
1&
b101 (
#2280000
0!
0&
#2290000
1!
1&
b110 (
#2300000
0!
0&
#2310000
1!
1&
b111 (
#2320000
0!
0&
#2330000
1!
1&
b1000 (
#2340000
0!
0&
#2350000
1!
1&
b1001 (
#2360000
0!
0&
#2370000
1!
1&
b1010 (
#2380000
0!
0&
#2390000
1!
1&
b1011 (
#2400000
0!
0&
#2410000
1!
1&
b1100 (
#2420000
0!
0&
#2430000
1!
1&
b1101 (
#2440000
0!
0&
#2450000
1!
1&
b1110 (
#2460000
0!
0&
#2470000
1!
1&
b1111 (
#2480000
0!
0&
#2490000
1!
1&
b10000 (
#2500000
0!
0&
#2510000
1!
1&
b10001 (
#2520000
0!
0&
#2530000
1!
1&
b10010 (
#2540000
0!
0&
#2550000
1!
1&
b10011 (
#2560000
0!
0&
#2570000
1!
1&
b10100 (
#2580000
0!
0&
#2590000
1!
1&
b10101 (
#2600000
0!
0&
#2610000
1!
1&
b10110 (
#2620000
0!
0&
#2630000
1!
1&
b10111 (
#2640000
0!
0&
#2650000
1!
1&
b11000 (
#2660000
0!
0&
#2670000
1!
1&
b11001 (
#2680000
0!
0&
#2690000
1!
1&
b11010 (
#2700000
0!
0&
#2710000
1!
1&
b11011 (
#2720000
0!
0&
#2730000
1!
1&
b11100 (
#2740000
0!
0&
#2750000
1!
1&
b11101 (
#2760000
0!
0&
#2770000
1!
1&
b11110 (
#2780000
0!
0&
#2790000
1!
1&
b11111 (
#2800000
0!
0&
#2810000
1!
1&
b100000 (
#2820000
0!
0&
#2830000
1!
1&
b100001 (
#2840000
0!
0&
#2850000
1!
1&
b100010 (
#2860000
0!
0&
#2870000
1!
1&
b100011 (
#2880000
0!
0&
#2890000
1!
1&
b100100 (
#2900000
0!
0&
#2910000
1!
1&
b100101 (
#2920000
0!
0&
#2930000
1!
1&
b100110 (
#2940000
0!
0&
#2950000
1!
1&
b100111 (
#2960000
0!
0&
#2970000
1!
1&
b101000 (
#2980000
0!
0&
#2990000
1!
1&
b101001 (
#3000000
0!
0&
#3010000
1!
1&
b101010 (
#3020000
0!
0&
#3030000
1!
1&
b101011 (
#3040000
0!
0&
#3050000
1!
1&
b101100 (
#3060000
0!
0&
#3070000
1!
1&
b101101 (
#3080000
0!
0&
#3090000
1!
1&
b101110 (
#3100000
0!
0&
#3110000
1!
1&
b101111 (
#3120000
0!
0&
#3130000
1!
1&
b110000 (
#3140000
0!
0&
#3150000
1!
1&
b110001 (
#3160000
0!
0&
#3170000
1!
1$
1&
b0 (
#3180000
0!
0&
#3190000
1!
b11 #
0$
1&
b1 (
#3200000
0!
0&
#3210000
1!
1&
b10 (
#3220000
0!
0&
#3230000
1!
1&
b11 (
#3240000
0!
0&
#3250000
1!
1&
b100 (
#3260000
0!
0&
#3270000
1!
1&
b101 (
#3280000
0!
0&
#3290000
1!
1&
b110 (
#3300000
0!
0&
#3310000
1!
1&
b111 (
#3320000
0!
0&
#3330000
1!
1&
b1000 (
#3340000
0!
0&
#3350000
1!
1&
b1001 (
#3360000
0!
0&
#3370000
1!
1&
b1010 (
#3380000
0!
0&
#3390000
1!
1&
b1011 (
#3400000
0!
0&
#3410000
1!
1&
b1100 (
#3420000
0!
0&
#3430000
1!
1&
b1101 (
#3440000
0!
0&
#3450000
1!
1&
b1110 (
#3460000
0!
0&
#3470000
1!
1&
b1111 (
#3480000
0!
0&
#3490000
1!
1&
b10000 (
#3500000
0!
0&
#3510000
1!
1&
b10001 (
#3520000
0!
0&
#3530000
1!
1&
b10010 (
#3540000
0!
0&
#3550000
1!
1&
b10011 (
#3560000
0!
0&
#3570000
1!
1&
b10100 (
#3580000
0!
0&
#3590000
1!
1&
b10101 (
#3600000
0!
0&
#3610000
1!
1&
b10110 (
#3620000
0!
0&
#3630000
1!
1&
b10111 (
#3640000
0!
0&
#3650000
1!
1&
b11000 (
#3660000
0!
0&
#3670000
1!
1&
b11001 (
#3680000
0!
0&
#3690000
1!
1&
b11010 (
#3700000
0!
0&
#3710000
1!
1&
b11011 (
#3720000
0!
0&
#3730000
1!
1&
b11100 (
#3740000
0!
0&
#3750000
1!
1&
b11101 (
#3760000
0!
0&
#3770000
1!
1&
b11110 (
#3780000
0!
0&
#3790000
1!
1&
b11111 (
#3800000
0!
0&
#3810000
1!
1&
b100000 (
#3820000
0!
0&
#3830000
1!
1&
b100001 (
#3840000
0!
0&
#3850000
1!
1&
b100010 (
#3860000
0!
0&
#3870000
1!
1&
b100011 (
#3880000
0!
0&
#3890000
1!
1&
b100100 (
#3900000
0!
0&
#3910000
1!
1&
b100101 (
#3920000
0!
0&
#3930000
1!
1&
b100110 (
#3940000
0!
0&
#3950000
1!
1&
b100111 (
#3960000
0!
0&
#3970000
1!
1&
b101000 (
#3980000
0!
0&
#3990000
1!
1&
b101001 (
#4000000
0!
0&
#4010000
1!
1&
b101010 (
#4020000
0!
0&
#4030000
1!
1&
b101011 (
#4040000
0!
0&
#4050000
1!
1&
b101100 (
#4060000
0!
0&
#4070000
1!
1&
b101101 (
#4080000
0!
0&
#4090000
1!
1&
b101110 (
#4100000
0!
0&
#4110000
1!
1&
b101111 (
#4120000
0!
0&
#4130000
1!
1&
b110000 (
#4140000
0!
0&
#4150000
1!
1&
b110001 (
#4160000
0!
0&
#4170000
1!
1$
1&
b0 (
#4180000
0!
0&
#4190000
1!
b100 #
0$
1&
b1 (
#4200000
0!
0&
#4210000
1!
1&
b10 (
#4220000
0!
0&
#4230000
1!
1&
b11 (
#4240000
0!
0&
#4250000
1!
1&
b100 (
#4260000
0!
0&
#4270000
1!
1&
b101 (
#4280000
0!
0&
#4290000
1!
1&
b110 (
#4300000
0!
0&
#4310000
1!
1&
b111 (
#4320000
0!
0&
#4330000
1!
1&
b1000 (
#4340000
0!
0&
#4350000
1!
1&
b1001 (
#4360000
0!
0&
#4370000
1!
1&
b1010 (
#4380000
0!
0&
#4390000
1!
1&
b1011 (
#4400000
0!
0&
#4410000
1!
1&
b1100 (
#4420000
0!
0&
#4430000
1!
1&
b1101 (
#4440000
0!
0&
#4450000
1!
1&
b1110 (
#4460000
0!
0&
#4470000
1!
1&
b1111 (
#4480000
0!
0&
#4490000
1!
1&
b10000 (
#4500000
0!
0&
#4510000
1!
1&
b10001 (
#4520000
0!
0&
#4530000
1!
1&
b10010 (
#4540000
0!
0&
#4550000
1!
1&
b10011 (
#4560000
0!
0&
#4570000
1!
1&
b10100 (
#4580000
0!
0&
#4590000
1!
1&
b10101 (
#4600000
0!
0&
#4610000
1!
1&
b10110 (
#4620000
0!
0&
#4630000
1!
1&
b10111 (
#4640000
0!
0&
#4650000
1!
1&
b11000 (
#4660000
0!
0&
#4670000
1!
1&
b11001 (
#4680000
0!
0&
#4690000
1!
1&
b11010 (
#4700000
0!
0&
#4710000
1!
1&
b11011 (
#4720000
0!
0&
#4730000
1!
1&
b11100 (
#4740000
0!
0&
#4750000
1!
1&
b11101 (
#4760000
0!
0&
#4770000
1!
1&
b11110 (
#4780000
0!
0&
#4790000
1!
1&
b11111 (
#4800000
0!
0&
#4810000
1!
1&
b100000 (
#4820000
0!
0&
#4830000
1!
1&
b100001 (
#4840000
0!
0&
#4850000
1!
1&
b100010 (
#4860000
0!
0&
#4870000
1!
1&
b100011 (
#4880000
0!
0&
#4890000
1!
1&
b100100 (
#4900000
0!
0&
#4910000
1!
1&
b100101 (
#4920000
0!
0&
#4930000
1!
1&
b100110 (
#4940000
0!
0&
#4950000
1!
1&
b100111 (
#4960000
0!
0&
#4970000
1!
1&
b101000 (
#4980000
0!
0&
#4990000
1!
1&
b101001 (
#5000000
0!
0&
#5010000
1!
1&
b101010 (
#5020000
0!
0&
#5030000
1!
1&
b101011 (
#5040000
0!
0&
#5050000
1!
1&
b101100 (
#5060000
0!
0&
#5070000
1!
1&
b101101 (
#5080000
0!
0&
#5090000
1!
1&
b101110 (
#5100000
0!
0&
#5110000
1!
1&
b101111 (
#5120000
0!
0&
#5130000
1!
1&
b110000 (
#5140000
0!
0&
#5150000
1!
1&
b110001 (
#5160000
0!
0&
#5170000
1!
1$
1&
b0 (
#5180000
0!
0&
#5190000
1!
b101 #
0$
1&
b1 (
#5200000
0!
0&
#5210000
1!
1&
b10 (
#5220000
0!
0&
#5230000
1!
1&
b11 (
#5240000
0!
0&
#5250000
1!
1&
b100 (
#5260000
0!
0&
#5270000
1!
1&
b101 (
#5280000
0!
0&
#5290000
1!
1&
b110 (
#5300000
0!
0&
#5310000
1!
1&
b111 (
#5320000
0!
0&
#5330000
1!
1&
b1000 (
#5340000
0!
0&
#5350000
1!
1&
b1001 (
#5360000
0!
0&
#5370000
1!
1&
b1010 (
#5380000
0!
0&
#5390000
1!
1&
b1011 (
#5400000
0!
0&
#5410000
1!
1&
b1100 (
#5420000
0!
0&
#5430000
1!
1&
b1101 (
#5440000
0!
0&
#5450000
1!
1&
b1110 (
#5460000
0!
0&
#5470000
1!
1&
b1111 (
#5480000
0!
0&
#5490000
1!
1&
b10000 (
#5500000
0!
0&
#5510000
1!
1&
b10001 (
#5520000
0!
0&
#5530000
1!
1&
b10010 (
#5540000
0!
0&
#5550000
1!
1&
b10011 (
#5560000
0!
0&
#5570000
1!
1&
b10100 (
#5580000
0!
0&
#5590000
1!
1&
b10101 (
#5600000
0!
0&
#5610000
1!
1&
b10110 (
#5620000
0!
0&
#5630000
1!
1&
b10111 (
#5640000
0!
0&
#5650000
1!
1&
b11000 (
#5660000
0!
0&
#5670000
1!
1&
b11001 (
#5680000
0!
0&
#5690000
1!
1&
b11010 (
#5700000
0!
0&
#5710000
1!
1&
b11011 (
#5720000
0!
0&
#5730000
1!
1&
b11100 (
#5740000
0!
0&
#5750000
1!
1&
b11101 (
#5760000
0!
0&
#5770000
1!
1&
b11110 (
#5780000
0!
0&
#5790000
1!
1&
b11111 (
#5800000
0!
0&
#5810000
1!
1&
b100000 (
#5820000
0!
0&
#5830000
1!
1&
b100001 (
#5840000
0!
0&
#5850000
1!
1&
b100010 (
#5860000
0!
0&
#5870000
1!
1&
b100011 (
#5880000
0!
0&
#5890000
1!
1&
b100100 (
#5900000
0!
0&
#5910000
1!
1&
b100101 (
#5920000
0!
0&
#5930000
1!
1&
b100110 (
#5940000
0!
0&
#5950000
1!
1&
b100111 (
#5960000
0!
0&
#5970000
1!
1&
b101000 (
#5980000
0!
0&
#5990000
1!
1&
b101001 (
#6000000
0!
0&
#6010000
1!
1&
b101010 (
#6020000
0!
0&
#6030000
1!
1&
b101011 (
#6040000
0!
0&
#6050000
1!
1&
b101100 (
#6060000
0!
0&
#6070000
1!
1&
b101101 (
#6080000
0!
0&
#6090000
1!
1&
b101110 (
#6100000
0!
0&
#6110000
1!
1&
b101111 (
#6120000
0!
0&
#6130000
1!
1&
b110000 (
#6140000
0!
0&
#6150000
1!
1&
b110001 (
#6160000
0!
0&
#6170000
1!
1$
1&
b0 (
#6180000
0!
0&
#6190000
1!
b110 #
0$
1&
b1 (
#6200000
0!
0&
#6210000
1!
1&
b10 (
#6220000
0!
0&
#6230000
1!
1&
b11 (
#6240000
0!
0&
#6250000
1!
1&
b100 (
#6260000
0!
0&
#6270000
1!
1&
b101 (
#6280000
0!
0&
#6290000
1!
1&
b110 (
#6300000
0!
0&
#6310000
1!
1&
b111 (
#6320000
0!
0&
#6330000
1!
1&
b1000 (
#6340000
0!
0&
#6350000
1!
1&
b1001 (
#6360000
0!
0&
#6370000
1!
1&
b1010 (
#6380000
0!
0&
#6390000
1!
1&
b1011 (
#6400000
0!
0&
#6410000
1!
1&
b1100 (
#6420000
0!
0&
#6430000
1!
1&
b1101 (
#6440000
0!
0&
#6450000
1!
1&
b1110 (
#6460000
0!
0&
#6470000
1!
1&
b1111 (
#6480000
0!
0&
#6490000
1!
1&
b10000 (
#6500000
0!
0&
#6510000
1!
1&
b10001 (
#6520000
0!
0&
#6530000
1!
1&
b10010 (
#6540000
0!
0&
#6550000
1!
1&
b10011 (
#6560000
0!
0&
#6570000
1!
1&
b10100 (
#6580000
0!
0&
#6590000
1!
1&
b10101 (
#6600000
0!
0&
#6610000
1!
1&
b10110 (
#6620000
0!
0&
#6630000
1!
1&
b10111 (
#6640000
0!
0&
#6650000
1!
1&
b11000 (
#6660000
0!
0&
#6670000
1!
1&
b11001 (
#6680000
0!
0&
#6690000
1!
1&
b11010 (
#6700000
0!
0&
#6710000
1!
1&
b11011 (
#6720000
0!
0&
#6730000
1!
1&
b11100 (
#6740000
0!
0&
#6750000
1!
1&
b11101 (
#6760000
0!
0&
#6770000
1!
1&
b11110 (
#6780000
0!
0&
#6790000
1!
1&
b11111 (
#6800000
0!
0&
#6810000
1!
1&
b100000 (
#6820000
0!
0&
#6830000
1!
1&
b100001 (
#6840000
0!
0&
#6850000
1!
1&
b100010 (
#6860000
0!
0&
#6870000
1!
1&
b100011 (
#6880000
0!
0&
#6890000
1!
1&
b100100 (
#6900000
0!
0&
#6910000
1!
1&
b100101 (
#6920000
0!
0&
#6930000
1!
1&
b100110 (
#6940000
0!
0&
#6950000
1!
1&
b100111 (
#6960000
0!
0&
#6970000
1!
1&
b101000 (
#6980000
0!
0&
#6990000
1!
1&
b101001 (
#7000000
0!
0&
#7010000
1!
1&
b101010 (
#7020000
0!
0&
#7030000
1!
1&
b101011 (
#7040000
0!
0&
#7050000
1!
1&
b101100 (
#7060000
0!
0&
#7070000
1!
1&
b101101 (
#7080000
0!
0&
#7090000
1!
1&
b101110 (
#7100000
0!
0&
#7110000
1!
1&
b101111 (
#7120000
0!
0&
#7130000
1!
1&
b110000 (
#7140000
0!
0&
#7150000
1!
1&
b110001 (
#7160000
0!
0&
#7170000
1!
1$
1&
b0 (
#7180000
0!
0&
#7190000
1!
b111 #
0$
1&
b1 (
#7200000
0!
0&
#7210000
1!
1&
b10 (
#7220000
0!
0&
#7230000
1!
1&
b11 (
#7240000
0!
0&
#7250000
1!
1&
b100 (
#7260000
0!
0&
#7270000
1!
1&
b101 (
#7280000
0!
0&
#7290000
1!
1&
b110 (
#7300000
0!
0&
#7310000
1!
1&
b111 (
#7320000
0!
0&
#7330000
1!
1&
b1000 (
#7340000
0!
0&
#7350000
1!
1&
b1001 (
#7360000
0!
0&
#7370000
1!
1&
b1010 (
#7380000
0!
0&
#7390000
1!
1&
b1011 (
#7400000
0!
0&
#7410000
1!
1&
b1100 (
#7420000
0!
0&
#7430000
1!
1&
b1101 (
#7440000
0!
0&
#7450000
1!
1&
b1110 (
#7460000
0!
0&
#7470000
1!
1&
b1111 (
#7480000
0!
0&
#7490000
1!
1&
b10000 (
#7500000
0!
0&
#7510000
1!
1&
b10001 (
#7520000
0!
0&
#7530000
1!
1&
b10010 (
#7540000
0!
0&
#7550000
1!
1&
b10011 (
#7560000
0!
0&
#7570000
1!
1&
b10100 (
#7580000
0!
0&
#7590000
1!
1&
b10101 (
#7600000
0!
0&
#7610000
1!
1&
b10110 (
#7620000
0!
0&
#7630000
1!
1&
b10111 (
#7640000
0!
0&
#7650000
1!
1&
b11000 (
#7660000
0!
0&
#7670000
1!
1&
b11001 (
#7680000
0!
0&
#7690000
1!
1&
b11010 (
#7700000
0!
0&
#7710000
1!
1&
b11011 (
#7720000
0!
0&
#7730000
1!
1&
b11100 (
#7740000
0!
0&
#7750000
1!
1&
b11101 (
#7760000
0!
0&
#7770000
1!
1&
b11110 (
#7780000
0!
0&
#7790000
1!
1&
b11111 (
#7800000
0!
0&
#7810000
1!
1&
b100000 (
#7820000
0!
0&
#7830000
1!
1&
b100001 (
#7840000
0!
0&
#7850000
1!
1&
b100010 (
#7860000
0!
0&
#7870000
1!
1&
b100011 (
#7880000
0!
0&
#7890000
1!
1&
b100100 (
#7900000
0!
0&
#7910000
1!
1&
b100101 (
#7920000
0!
0&
#7930000
1!
1&
b100110 (
#7940000
0!
0&
#7950000
1!
1&
b100111 (
#7960000
0!
0&
#7970000
1!
1&
b101000 (
#7980000
0!
0&
#7990000
1!
1&
b101001 (
#8000000
0!
0&
#8010000
1!
1&
b101010 (
#8020000
0!
0&
#8030000
1!
1&
b101011 (
#8040000
0!
0&
#8050000
1!
1&
b101100 (
#8060000
0!
0&
#8070000
1!
1&
b101101 (
#8080000
0!
0&
#8090000
1!
1&
b101110 (
#8100000
0!
0&
#8110000
1!
1&
b101111 (
#8120000
0!
0&
#8130000
1!
1&
b110000 (
#8140000
0!
0&
#8150000
1!
1&
b110001 (
#8160000
0!
0&
#8170000
1!
1$
1&
b0 (
#8180000
0!
0&
#8190000
1!
b1000 #
0$
1&
b1 (
#8200000
0!
0&
#8210000
1!
1&
b10 (
#8220000
0!
0&
#8230000
1!
1&
b11 (
#8240000
0!
0&
#8250000
1!
1&
b100 (
#8260000
0!
0&
#8270000
1!
1&
b101 (
#8280000
0!
0&
#8290000
1!
1&
b110 (
#8300000
0!
0&
#8310000
1!
1&
b111 (
#8320000
0!
0&
#8330000
1!
1&
b1000 (
#8340000
0!
0&
#8350000
1!
1&
b1001 (
#8360000
0!
0&
#8370000
1!
1&
b1010 (
#8380000
0!
0&
#8390000
1!
1&
b1011 (
#8400000
0!
0&
#8410000
1!
1&
b1100 (
#8420000
0!
0&
#8430000
1!
1&
b1101 (
#8440000
0!
0&
#8450000
1!
1&
b1110 (
#8460000
0!
0&
#8470000
1!
1&
b1111 (
#8480000
0!
0&
#8490000
1!
1&
b10000 (
#8500000
0!
0&
#8510000
1!
1&
b10001 (
#8520000
0!
0&
#8530000
1!
1&
b10010 (
#8540000
0!
0&
#8550000
1!
1&
b10011 (
#8560000
0!
0&
#8570000
1!
1&
b10100 (
#8580000
0!
0&
#8590000
1!
1&
b10101 (
#8600000
0!
0&
#8610000
1!
1&
b10110 (
#8620000
0!
0&
#8630000
1!
1&
b10111 (
#8640000
0!
0&
#8650000
1!
1&
b11000 (
#8660000
0!
0&
#8670000
1!
1&
b11001 (
#8680000
0!
0&
#8690000
1!
1&
b11010 (
#8700000
0!
0&
#8710000
1!
1&
b11011 (
#8720000
0!
0&
#8730000
1!
1&
b11100 (
#8740000
0!
0&
#8750000
1!
1&
b11101 (
#8760000
0!
0&
#8770000
1!
1&
b11110 (
#8780000
0!
0&
#8790000
1!
1&
b11111 (
#8800000
0!
0&
#8810000
1!
1&
b100000 (
#8820000
0!
0&
#8830000
1!
1&
b100001 (
#8840000
0!
0&
#8850000
1!
1&
b100010 (
#8860000
0!
0&
#8870000
1!
1&
b100011 (
#8880000
0!
0&
#8890000
1!
1&
b100100 (
#8900000
0!
0&
#8910000
1!
1&
b100101 (
#8920000
0!
0&
#8930000
1!
1&
b100110 (
#8940000
0!
0&
#8950000
1!
1&
b100111 (
#8960000
0!
0&
#8970000
1!
1&
b101000 (
#8980000
0!
0&
#8990000
1!
1&
b101001 (
#9000000
0!
0&
#9010000
1!
1&
b101010 (
#9020000
0!
0&
#9030000
1!
1&
b101011 (
#9040000
0!
0&
#9050000
1!
1&
b101100 (
#9060000
0!
0&
#9070000
1!
1&
b101101 (
#9080000
0!
0&
#9090000
1!
1&
b101110 (
#9100000
0!
0&
#9110000
1!
1&
b101111 (
#9120000
0!
0&
#9130000
1!
1&
b110000 (
#9140000
0!
0&
#9150000
1!
1&
b110001 (
#9160000
0!
0&
#9170000
1!
1$
1&
b0 (
#9180000
0!
0&
#9190000
1!
b1001 #
0$
1&
b1 (
#9200000
0!
0&
#9210000
1!
1&
b10 (
#9220000
0!
0&
#9230000
1!
1&
b11 (
#9240000
0!
0&
#9250000
1!
1&
b100 (
#9260000
0!
0&
#9270000
1!
1&
b101 (
#9280000
0!
0&
#9290000
1!
1&
b110 (
#9300000
0!
0&
#9310000
1!
1&
b111 (
#9320000
0!
0&
#9330000
1!
1&
b1000 (
#9340000
0!
0&
#9350000
1!
1&
b1001 (
#9360000
0!
0&
#9370000
1!
1&
b1010 (
#9380000
0!
0&
#9390000
1!
1&
b1011 (
#9400000
0!
0&
#9410000
1!
1&
b1100 (
#9420000
0!
0&
#9430000
1!
1&
b1101 (
#9440000
0!
0&
#9450000
1!
1&
b1110 (
#9460000
0!
0&
#9470000
1!
1&
b1111 (
#9480000
0!
0&
#9490000
1!
1&
b10000 (
#9500000
0!
0&
#9510000
1!
1&
b10001 (
#9520000
0!
0&
#9530000
1!
1&
b10010 (
#9540000
0!
0&
